{"metadata": {"dbt_schema_version": "https://schemas.getdbt.com/dbt/run-results/v4.json", "dbt_version": "1.0.0", "generated_at": "2021-12-16T11:30:28.727964Z", "invocation_id": "6397905f-bb8e-4162-8f22-311752d595a2", "env": {}}, "results": [{"status": "success", "timing": [{"name": "compile", "started_at": "2021-12-16T11:30:28.648231Z", "completed_at": "2021-12-16T11:30:28.667314Z"}, {"name": "execute", "started_at": "2021-12-16T11:30:28.667613Z", "completed_at": "2021-12-16T11:30:28.667640Z"}], "thread_id": "Thread-3", "execution_time": 0.019776582717895508, "adapter_response": {}, "message": null, "failures": null, "unique_id": "model.Modeling_1.my_first_dbt_model"}, {"status": "success", "timing": [{"name": "compile", "started_at": "2021-12-16T11:30:28.651805Z", "completed_at": "2021-12-16T11:30:28.668004Z"}, {"name": "execute", "started_at": "2021-12-16T11:30:28.668263Z", "completed_at": "2021-12-16T11:30:28.668271Z"}], "thread_id": "Thread-2", "execution_time": 0.01681065559387207, "adapter_response": {}, "message": null, "failures": null, "unique_id": "model.Modeling_1.model_cases"}, {"status": "success", "timing": [{"name": "compile", "started_at": "2021-12-16T11:30:28.669668Z", "completed_at": "2021-12-16T11:30:28.701584Z"}, {"name": "execute", "started_at": "2021-12-16T11:30:28.701854Z", "completed_at": "2021-12-16T11:30:28.701863Z"}], "thread_id": "Thread-5", "execution_time": 0.032503604888916016, "adapter_response": {}, "message": null, "failures": null, "unique_id": "model.Modeling_1.my_second_dbt_model"}, {"status": "success", "timing": [{"name": "compile", "started_at": "2021-12-16T11:30:28.677314Z", "completed_at": "2021-12-16T11:30:28.709725Z"}, {"name": "execute", "started_at": "2021-12-16T11:30:28.709980Z", "completed_at": "2021-12-16T11:30:28.709987Z"}], "thread_id": "Thread-3", "execution_time": 0.03294992446899414, "adapter_response": {}, "message": null, "failures": null, "unique_id": "test.Modeling_1.unique_my_first_dbt_model_id.16e066b321"}, {"status": "success", "timing": [{"name": "compile", "started_at": "2021-12-16T11:30:28.672326Z", "completed_at": "2021-12-16T11:30:28.710382Z"}, {"name": "execute", "started_at": "2021-12-16T11:30:28.710640Z", "completed_at": "2021-12-16T11:30:28.710648Z"}], "thread_id": "Thread-4", "execution_time": 0.03862142562866211, "adapter_response": {}, "message": null, "failures": null, "unique_id": "test.Modeling_1.not_null_my_first_dbt_model_id.5fb22c2710"}, {"status": "success", "timing": [{"name": "compile", "started_at": "2021-12-16T11:30:28.706862Z", "completed_at": "2021-12-16T11:30:28.724121Z"}, {"name": "execute", "started_at": "2021-12-16T11:30:28.724378Z", "completed_at": "2021-12-16T11:30:28.724385Z"}], "thread_id": "Thread-5", "execution_time": 0.01781940460205078, "adapter_response": {}, "message": null, "failures": null, "unique_id": "test.Modeling_1.unique_my_second_dbt_model_id.57a0f8c493"}, {"status": "success", "timing": [{"name": "compile", "started_at": "2021-12-16T11:30:28.702916Z", "completed_at": "2021-12-16T11:30:28.726097Z"}, {"name": "execute", "started_at": "2021-12-16T11:30:28.726358Z", "completed_at": "2021-12-16T11:30:28.726366Z"}], "thread_id": "Thread-2", "execution_time": 0.023793935775756836, "adapter_response": {}, "message": null, "failures": null, "unique_id": "test.Modeling_1.not_null_my_second_dbt_model_id.151b76d778"}], "elapsed_time": 0.8486628532409668, "args": {"write_json": true, "use_colors": true, "printer_width": 80, "version_check": true, "partial_parse": true, "static_parser": true, "profiles_dir": "/usr/src/develop/.dbt", "send_anonymous_usage_stats": true, "profile": "user", "host": "0.0.0.0", "port": 8580, "which": "rpc", "compile": true, "indirect_selection": "eager", "event_buffer_size": 100000}}